CSC_600_Lab1_CurrentTimeWebApp-1.0.8.data/scripts/webapp-timesync.py
csc_cyb600_TSL1/__init__.py
csc_cyb600_TSL1/app.py
CSC_600_Lab1_CurrentTimeWebApp-1.0.8.dist-info/LICENSE
CSC_600_Lab1_CurrentTimeWebApp-1.0.8.dist-info/METADATA
CSC_600_Lab1_CurrentTimeWebApp-1.0.8.dist-info/WHEEL
CSC_600_Lab1_CurrentTimeWebApp-1.0.8.dist-info/top_level.txt
CSC_600_Lab1_CurrentTimeWebApp-1.0.8.dist-info/RECORD
